ddns_client/__init__.py
ddns_client/ddns_client.py
ddns_client/get_args.yml
ddns_client-0.8.dist-info/LICENSE
ddns_client-0.8.dist-info/METADATA
ddns_client-0.8.dist-info/WHEEL
ddns_client-0.8.dist-info/entry_points.txt
ddns_client-0.8.dist-info/top_level.txt
ddns_client-0.8.dist-info/RECORD
