Metadata-Version: 2.1
Name: ddns-client
Version: 0.8
Summary: ddns_client, used with coredns/etcd
Home-page: https://github.com/fun04wr0ng/ddns
Author: fun04wr0ng
Author-email: fun04wr0ng@gmail.com
License: GPL v3
Platform: UNKNOWN
Classifier: Programming Language :: Python :: 3.6
Classifier: License :: OSI Approved :: GNU General Public License v3 or later (GPLv3+)
Classifier: Operating System :: Microsoft :: Windows :: Windows 10
Classifier: Operating System :: POSIX :: Linux
Requires-Python: >=3.6
Requires-Dist: get-args (>=1.2)
Requires-Dist: aiohttp[speedups]
Provides-Extra: color
Requires-Dist: coloredlogs ; extra == 'color'
Provides-Extra: etcd
Requires-Dist: etcd3 ; extra == 'etcd'
Provides-Extra: fluentd
Requires-Dist: fluent-logger ; extra == 'fluentd'
Provides-Extra: prometheus
Requires-Dist: prometheus-client ; extra == 'prometheus'
Provides-Extra: statsd
Requires-Dist: statsd ; extra == 'statsd'
